tpds_extension/cloud_connect/extension.yaml
tpds_extension/cloud_connect/setup.py
tpds_extension/cloud_connect/version.py
tpds_extension/cloud_connect/TrustFlex/AWS Connect-Custom PKI-TFLEX.ipynb
tpds_extension/cloud_connect/TrustFlex/AWS Connect-IoT Auth-TFLEX.ipynb
tpds_extension/cloud_connect/TrustFlex/Azure Connect-Custom PKI-TFLEX.ipynb
tpds_extension/cloud_connect/TrustFlex/Azure Connect-IoT Auth-TFLEX.ipynb
tpds_extension/cloud_connect/TrustFlex/Azure Connect-RTOS-TFLEX.ipynb
tpds_extension/cloud_connect/TrustFlex/aws_connect.h
tpds_extension/cloud_connect/TrustFlex/azure_connect.h
tpds_extension/cloud_connect/TrustFlex/cust_def_device.c
tpds_extension/cloud_connect/TrustFlex/cust_def_device.h
tpds_extension/cloud_connect/TrustFlex/cust_def_signer.c
tpds_extension/cloud_connect/TrustFlex/cust_def_signer.h
tpds_extension/cloud_connect/TrustFlex/firmware.zip
tpds_extension/cloud_connect/TrustFlex/google_connect.h
tpds_extension/cloud_connect/TrustFlex/project_config.h
tpds_extension/cloud_connect/TrustFlex/assets/AWS Connect.md
tpds_extension/cloud_connect/TrustFlex/assets/Azure Connect.md
tpds_extension/cloud_connect/TrustFlex/assets/aws-zero-touch-full-setup-cn.yaml
tpds_extension/cloud_connect/TrustFlex/assets/aws-zero-touch-full-setup.yaml
tpds_extension/cloud_connect/TrustFlex/assets/aws_trust.ui
tpds_extension/cloud_connect/TrustFlex/assets/azureRTOS_use_doc.md
tpds_extension/cloud_connect/TrustFlex/assets/gcp_trust.ui
tpds_extension/cloud_connect/TrustFlex/assets/shield.ico
tpds_extension/cloud_connect/TrustFlex/assets/images/AWS.png
tpds_extension/cloud_connect/TrustFlex/assets/images/Azure.png
tpds_extension/cloud_connect/TrustFlex/assets/images/GCP.png
tpds_extension/cloud_connect/TrustFlex/assets/images/assets_custompki_aws_azure.png
tpds_extension/cloud_connect/TrustFlex/assets/images/assets_custompki_google.png
tpds_extension/cloud_connect/TrustFlex/assets/images/aws_ttlog.png
tpds_extension/cloud_connect/TrustFlex/assets/images/azure_ttlog.png
tpds_extension_spg_cloud_connect-2.3.5.dist-info/METADATA
tpds_extension_spg_cloud_connect-2.3.5.dist-info/WHEEL
tpds_extension_spg_cloud_connect-2.3.5.dist-info/top_level.txt
tpds_extension_spg_cloud_connect-2.3.5.dist-info/RECORD
